{
	"Selected Start Time": "Data Inizio Selezionata",
	"Selected End Time": "Data Fine Selezionata",
	"Invalid activity. The project to which it belongs and the environment prefix in the template do not match": "Activity non valida. Il progetto a cui appartiene e la chiave 'environment_prefix' nel payload non corrispondono",
	"INVALID RATES SETTINGS: Lower Rate must be lower then the Higher Rate": "SETTAGGIO SOGLIE INVALIDO: Il rateo della soglia Minima deve essere minore di quella Massima",
	"Threshold not set": "Soglia non settata",
	"Please select App Name and Version": "Scegliere Nome e Versione del pacchetto",
	"Completed": "Completato",
	"In Progress": "In Corso",
	"Timeout": "In Timeout",
	"Partial": "Parziale",
	"Deletion": "Cancellazione",
	"completed": "completato",
	"Add": "Aggiungi",
	"All": "Tutti",
	"ALL": "Tutti",
	"all": "tutti",
	"notifications": "notifiche",
	"errors": "errori",
	"Greengrass is INSTALLED": "Greengrass è INSTALLATO",
	"Greengrass is NOT INSTALLED": "Greengrass NON è INSTALLATO",
	"thing paired successfully": "Thing attivata con successo",
	"unable to pair thing: an exception occurred while registering thing with AWS": "Impossibile attivare thing. Errore registrazione con AWS",
	"unable to unpair thing: an exception occurred while deregistering thing with AWS": "Impossibile deattivare thing. Errore registrazione con AWS",
	"gateway monitor activated": "Gateway monitoring attivato",
	"gateway monitor deactivated": "Gateway monitoring deattivato",
	"Local Proxy Activated": "Local proxy attivato",
	"thing unpaired successfully": "Thing disattivata con successo",
	"snap update without reboot successfully completed": "Aggiornamento snap completato con successo",
	"log manager activated": "Log manager attivato",
	"Message": "Messaggio",
	"log manager deactivated": "Log manager deattivato",
	"Download is ready": "Download pronto",
	"The Deployment is": "Lo stato del rilascio è:",
	"thing_alarm": "Dispositivo",
	"behavior": "Funzionale",
	"device_alarm": "device alarm",
	"thing_event": "thing event",
	"platform_log": "platform log",
	"log": "Log",
	"Select": "Apri",
	"Click here": "Scarica",
	"Start Time": "Inizio",
	"End Time": "Fine",
	"connected": "connected",
	"activated": "attivo",
	"disconnected": "disconnected",
	"connected_only_app": "connesso solo app",
	"connected_only_net": "connesso solo rete",
	"SUCCEEDED": "Completato",
	"IN_PROGRESS": "In corso",
	"FAILED": "Fallito",
	"theGatewayIs": "Il Gateway è ",
	"The thing is": "Il dispositvo è ",
	"Installed software": "Software installati ",
	"Devices": "Dispositivi",
	"Gateway": "Gateway",
	"Thing": "Thing",
	"UpdateThingSuccess": "Thing aggiornata con successo",
	"UpdateThingFailed": "Aggiornamento thing fallito",
	"DirectThing": "Direct Thing",
	"map": "Nazione",
	"target": "Destinatario",
	"Projects": "Progetti",
	"Meters": "Misuratori",
	"Meters List": "Lista Misuratori",
	"Serial Number": "Numero Seriale",
	"Project": "Progetto",
	"Registry": "Anagrafica",
	"Name": "Nome",
	"Search project": "Cerca Progetto",
	"Project Info": "Informazioni Progetto",
	"Site": "Sito",
	"Actions": "Azioni",
	"Meters Map": "Mappa Misuratori",
	"Search meter": "Cerca misuratore",
	"Data Retrieval": "Recupero Dati",
	"Commands": "Comandi",
	"Set Clock": "Imposta Orario",
	"Set Clock Command History": "Storico comandi regolazione orario",
	"Data Extraction": "Estrazione Dati",
	"Start Date": "Data Inizio",
	"End Date": "Data Fine",
	"Reset": "Pulisci",
	"Confirm": "Conferma",
	"Project Detail": "Dettaglio Progetto",
	"Info": "Informazioni",
	"Attachment": "Allegato",
	"Project Id": "Id Progetto",
	"Description": "Descrizione",
	"Meters to add": "Misuratori da aggiungere",
	"No meters selected": "Nessun misuratore selezionato",
	"Back to projects": "Torna ai progetti",
	"SearchProjects": "Cerca i progetti",
	"fullAccess": "Accesso Totale",
	"partialAccess": "Accesso Parziale",
	"Save": "Salva",
	"required": "Campo obbligatorio",
	"Back": "Indietro",
	"Exit": "Esci",
	"No files": "Nessun File",
	"You can upload a file": "Puoi caricare un file",
	"Click on the button and choose a file": "Clicca sul bottone e scegli un file",
	"Select file": "Seleziona un file",
	"File name": "Nome file",
	"Upload file": "Upload file",
	"Unable to upload a file: This file type is not supported": "Impossibile caricare il file: questo tipo di file non è supportato",
	"Type": "Tipo",
	"Size": "Dimensione",
	"Memory": "Memoria",
	"Logout": "Esci",
	"UserSettings": "Esci / Profilo / Lingua / Gruppi",
	"UserProfile": "Profilo",
	"Groups": "Grouppi",
	"Meter Detail": "Dettaglio Misuratore",
	"Meter Info": "Informazioni Misuratore",
	"Meter Id": "Id Misuratore",
	"Thing Id": "Thing Id",
	"Location": "Posizione",
	"City": "Città",
	"Area": "Area",
	"Address": "Indirizzo",
	"Coordinates": "Coordinate",
	"Validation error": "Errore validazione",
	"Sim": "Sim",
	"Sim Number": "Numero Sim",
	"Sim Username": "Sim Username",
	"Back to map": "Torna alla mappa",
	"Back to meters": "Torna ai misuratori",
	"Add Meters": "Aggiungi Misuratori",
	"Select one or more meters and add them to the project": "Seleziona uno o più meters per aggiungerli al progetto",
	"Cancel": "Cancella",
	"Next": "Avanti",
	"Warning!": "Attenzione!",
	"Warning": "Attenzione",
	"Ok": "Ok",
	"Success": "Successo",
	"Error": "Errore",
	"serverError": "Errore Server",
	"Delete Project": "Cancella Progetto",
	"Are you sure to delete the project?": "Sei sicuro di voler cancellare il progetto?",
	"Delete Projects": "Delete Projects",
	"genericDeleteTitle": "Elemina elemento selezionato",
	"genericDeleteQuestion": "Sei sicuro di voler eliminare l'elemento selezionato?",
	"Are you sure to delete the selected projects?": "Sei sicuro di voler cancellare il progetto selezionato?",
	"Delete Meter": "Cancella Misuratore",
	"Are you sure to delete the meter?": "Sei sicuro di voler cancellare il misuratore?",
	"Delete Meters": "Cancella Misuratori",
	"Are you sure to delete the selected meters?": "Sei sicuro di voler cancellare il misuratore selezionato?",
	"Meter Informations": "Informazioni Misuratore",
	"Delete Attachment": "Elimina allegato",
	"Are you sure to delete the attachment?": "Sei sicuro di voler eliminare l'allegato?",
	"Job Submitted": "Job Inviato",
	"Jobs List": "Lista jobs",
	"Contact Us": "Contattaci",
	"Learn More": "Ulteriori Informazioni",
	"meterPendingUpdates": "Ci sono delle modifiche non salvate. Si prega di salvarle o tornare alla lista dei misuratori",
	"meterPendingUpdatesMap": "Ci sono delle modifiche non salvate. Si prega di salvarle o tornare alla mappa dei misuratori",
	"projectPendingUpdates": "Ci sono delle modifiche non salvate. Si prega di salvarle o tornare alla lista dei progetti",
	"Potenza attiva": "Potenza attiva",
	"Energia attiva": "Energia attiva",
	"Telemetry": "Telemetria",
	"Close": "Chiudi",
	"lastCollectLogs": "Ultima invocazione del comando Collect logs: ",
	"currently": "Attualmente",
	"enabled": "Abilitato",
	"disabled": "Disabilitato",
	"Please wait ...": "Attendere ...",
	"LOW": "BASSO",
	"HIGH": "ALTO",
	"tap a column" : "Tocca una colonna per visualizzare i dati di ciascuna barra",
	"mutuallyExclusive":"I due campi Gateway Type e Thing Type sono obbligatori e mutuamente esculusivi",
	"projectList": {
		"selectProjects": "Progetti Selezionati: ",
		"projects": "Progetti",
		"enter": "Entra",
		"clear": "Cancella",
		"warnCrossProject": "In caso di scelta multipla non tutte le funzionalità saranno disponibili.",
		"segregationMultiselectError":"Selezionando un progetto con cluster non puoi selezionare altri progetti",
		"noCompacGroupsFound": "Nessun gruppo CompAC trovato"
	},
	"meterDiaolog": {
		"update": {
			"success": "Misuratore {{meterId}} aggiornato con successo",
			"error": "Errore nell'aggiornamento del misuratore {{meterId}}"
		}
	},
	"projectDiaolog": {
		"update": {
			"success": "Progetto {{projectName}} aggiornato con successo",
			"error": "Errore nell'aggiornamento del progetto {{projectName}}"
		},
		"create": {
			"success": "Progetto {{projectName}} creato con successo",
			"error": "Errore nella creazione del progetto"
		}
	},
	"activities": {
		"addActivity": "Aggiungi Attività",
		"editActivity": "Modifica Attività",
		"copyActivity": "Copia Attività",
		"activityId": "ID Attività",
		"deviceSn": "SN DISPOSITIVO",
		"insertActivityId": "Digita l'id attività qui...",
		"insertActivityNotes":"Scrivi qui le tue note...",
		"activityRequired": "Id Attività è obbligatorio",
		"template": "Template",
		"editConfirmActivity": "Salva modifiche",
		"runActivitySuccess": "Attività eseguita con successo",
		"runActivityError": "Impossibile eseguire l'attività",
		"createActivitySuccess": "Attività creata con successo",
		"deleteActivitySuccess": "eliminato con successo",
		"deleteActivityError": "Impossibile eliminare l'attività",
		"editActivitySuccess": "Attività modificata con successo",
		"copyActivitySuccess": "Attività copiata con successo",
		"writeOperationActivityError": "Impossibile eseguire l'operazione sull'attività",
		"error_ActivityNotAuthorized": "L'utente non è autorizzato ad eseguire questa operazione su questo specifico dispositivo",
		"errorDuplicateActivity": "L'attività con id {{activityId}} è già presente",
		"searchActivities": "Cerca per ID Attività",
		"thingId": "ID Thing",
		"thingSerialNumber": "SN Thing",
		"thingAlias": "Alias Thing"
	},
	"alarms": {
		"Alarms": "Logs & Allarmi",
		"SearchAlarms": "Cerca Allarmi",
		"NoAlarmsFound": "Nessun allarme trovato",
		"Status": "Stato",
		"CommCode": "Codice Evento",
		"CommCodeDesc": "Descrizione Evento ",
		"Timestamp": "Data",
		"TimestampResolved": "Data risoluzione",
		"Device is not answering": "Il dispositivo non risponde",
		"Device is on line": "Il dispositivo è on-line",
		"alarmsExporting": "Esportazione Allarmi",
		"logsExporting": "Esportazione Log",
		"alarmsExportTotalItems": "Numero di allarmi da esportare",
		"logsExportTotalItems": "Numero di logs da esportare",
		"alarmsExportConfirm": "quest'operazione puo richiedere un po di tempo, procedere comunque?",
		"error": "error"
	},
	"controlRoom": {
		"mapTooltips": {
			"refresh": "Aggiorna dati",
			"fitBounds": "Adatta ai confini"
		},
		"serial": "Serial",
		"GatewayDetailPage": "Dettagli Gateway",
		"deviceID": "ID Dispositivo",
		"thingID": "ID Thing",
		"renewGatewayCertificate": "Rinnova certificato gateway",
		"searchFilters": "Filtri di Ricerca",
		"authorization": "Autorizzazione",
		"feature": "Caratteristica",
		"aggregatedData": "dati aggregati",
		"deleteButton": "Cancella",
		"rebootButton": "Riavvia",
		"deployButton": "Rilascio",
		"authorization_token": "Token Autenticazione",
		"usernamePassword": "Username e password",
		"resetButton": "Resetta",
		"alignButton": "Allinea",
		"connections": "Connessioni",
		"disconnections": "Disconnessioni",
		"lastConnection": "Ultima Connessione",
		"lastDisconnection": "Ultima Disconnessione",
		"directRemoteControl": "Controllo Remoto Diretto",
		"remoteControlCloseMessage": "Vuoi chiudere la connessione del tunnel?",
		"chooseFile": "Scegli un file...",
		"attach": "Allega",
		"greengrassCommands": "Comandi Greengrass",
		"greengrassDeploy": "Rilascio Greengrass",
		"geolocalizationFormatNotValid": {
			"lat": "Specificare le coordinate in base all'intervallo -90/90 utilizzando il '-' per coordinate negative e senza + per positive, ad es. -19.1234, 9.3456",
			"lon": "Specificare le coordinate in base all'intervallo -90/90 utilizzando il '-' per coordinate negative e senza + per positive, ad es. -123.12, 12.34"
		},
		"invalidInputCharactersRestricted": "I caratteri speciali (es. $, %, &, *, è) non sono validi.",
		"invalidInputCharactersRestrictedPassword": "Spazio vuoto non è ammesso.",
		"invalidInputCharactersRestrictedNumbers": "I caratteri validi sono numeri.",
		"invalidInputCharactersRestrictedWithHash": "I caratteri speciali (es. #, $, %, &, *, è) non sono validi.",
		"invalidInputCharactersRestrictedIpAddress": "L'indirizzo IP deve avere il formato IPv4 (ad es. 192.168.1.100).",
		"invalidInputCharacters": "Non puoi usare caratteri speciali!",
		"defaultTooltipValue": "Clicca per maggiori informazioni",
		"featureNotAvailable": "Questa funzionalità non è disponibile se è stato selezionato più di un progetto",
		"alignGatewayDevicesStatusBottomSheetMessage": "Questa operazione potrebbe richiedere un po di tempo, vuoi allineare lo Stato del Gateway e di TUTTI i suoi Dispositivi?",
		"alignDevicesStatusBottomSheetMessage": "Questa operazione potrebbe richiedere un po di tempo, vuoi allineare gli Stati di TUTTI i Dispositivi?",
		"alignDeviceStatusConfirmTitle": "Allineamento Stati dei Dispositivi",
		"alignGatewayStatus": "Allinea gli Stati del Gateway e delle Things sottese",
		"alignGatewayStatusSuccess": "Stato gateway allineato con successo",
		"alignGatewayStatusError": "Impossibile allineare lo stato del gateway",
		"alignDevicesStatusSuccess": "Stati dei Dispositivi allineati con Successo, aggiornare la pagina per vedere gli aggiornamenti",
		"alignDevicesStatusFail": "Errore Allineamento Stati dei Dispostivi",
		"alignStatus": "Allinea Stati",
		"clearFilter": "Pulisci Filtro",
		"unknown": "Sconosciuto",
		"startTime": "Data Inizio",
		"endTime": "Data Fine",
		"infoTooltip": "Il livello INFO definisce messaggi informativi che sottolineano il progresso dell' applicazione ad un livello di granularità grande",
		"debugTooltip": "Il livello DEBUG definisce messaggi informativi con una granularità fine utile per la correzione di errori dei flussi",
		"warningTooltip": "Il livello WARNING definisce situazioni potenzialmente nocive",
		"errorTooltip": "Il livello ERROR definisce eventi di errore che potrebbero però permettere al flusso di continuare a lavorare",
		"criticalTooltip": "Il livello CRITICAL definisce eventi di errore molto gravi che pregiudicano il corretto funzionamento dei flussi",
		"activations": "Attivazioni",
		"alarms": "Allarmi & Eventi",
		"platform": "Piattaforma",
		"devices": "Dispositivi",
		"execution": "Esecuzione",
		"alarmsDevices": "Allarmi/Dispositivi",
		"customGroups": "Gruppi Personalizzati",
		"usageStatistics": "Statistiche di utilizzo",
		"projectName": "Nome Progetto",
		"groupName": "Nome Gruppo",
		"apiInvocation": "Invocazione API",
		"e2eMonitoring": "Monitoraggio E2E",
		"deploymentDetails": "Dettagli Distribuzione",
		"directThingDetailPage": "Pagina Dettaglio Direct Thing",
		"softwareManagement": "Aggiornamenti Software",
		"alias": "Alias",
		"note": "Nota",
		"notes": "Note",
		"release": "Rilascio",
		"infos": "Info",
		"moreInfos": "Info",
		"download": "Download",
		"activity": "Attività",
		"addActivity": "Agg. Attività",
		"addSite": "Aggiungi Sito",
		"map": "Nazione",
		"list": "Lista",
		"placeholderInfoPanelMap": "Tocca un placeholder per visualizzarne qui le info",
		"view": "Visualizza",
		"refresh": "Aggiorna",
		"delete": "Elimina",
		"run": "Lancia",
		"more": "Altro",
		"showDetails": "Mostra dettagli",
		"copy": "Copia",
		"subscribe": "Sottoscrivi",
		"systemCommands": "Comandi di Sistema",
		"thingStateLegend": "Icona GIALLA vuol dire che la thing è ATTIVATA,icona ROSSA vuol dire che la thing è DISCONNESSA,icona VERDE vuol dire che la thing è CONNESSA , icona BLU vuol dire che la thing è CONNESSA SOLO A LIVELLO APPLICATIVO, icona VERDEACQUA vuol dire che la thing è CONNESSA SOLO A LIVELLO DI RETE",
		"telemetry": "Telemetria",
		"thingsList": "Lista Things",
		"appVersion": "Versione: ",
		"devicesList": "Lista dispositivi",
		"general": "Generale",
		"orderBy": "Ordina per:",
		"orderDesc": "Ordine decrescente",
		"selectProjectMessageDescription": "Seleziona un progetto",
		"selectLambdaMessageDescription": "Seleziona una lambda",
		"autocompleteFilterInputLabel": "Autocompletamento On",
		"lambdaMonitoring": "Monitoraggio funzioni lambda",
		"mqttClient": "Interfaccia Mqtt",
		"devType": "Tipo dispositivo",
		"envPrefix": "Prefisso Ambiente",
		"envPrefixShort": "Ambiente",
		"maker": "Produttore",
		"searchPlaceholder": "Cerca qualcosa",
		"searchDevicesPlaceholder": "Cerca per ID, Seriale",
		"searchAlarmsPlaceholder": "Cerca per Source",
		"searchJobPlaceholder": "Cerca per ID dispositivo/ID oggetto (id,sn,alias)",
		"model": "Modello",
		"certificate": "Certificato",
		"actions": "Azioni",
		"thingDetail": "Dettaglio Thing",
		"directThingDetail": "Dettaglio Direct Thing",
		"gatewayDetail": "Dettaglio Gateway",
		"collectLogs": "Colleziona Logs",
		"checkinStatusCommand": "In attesa dello stato del comando...",
		"monitoring": "Monitoraggio",
		"thingsInError": "Things in errore",
		"deactivateTitle": "Stai disattivando il dispositivo: ",
		"bulkDevicesDeactivation": "Disattivazione Multipla dei Dispositivi",
		"deactivateMessage": "Sei sicuro?",
		"confirm": "Conferma",
		"cancel": "Annulla",
		"confirmText": "Che cosa vuoi fare?",
		"reboot": "Riavvia",
		"filters": "Filtri",
		"DeploySoftware": "Rilascio Software",
		"customQuery": "Query manuale",
		"value": "Valore",
		"rebootTitle": "Stai riavviando il dispositivo:",
		"firmware": "Aggiorna firmware",
		"updateGateway": "Aggiorna gateway",
		"remoteControl": "Controllo remoto",
		"activateThing": "Attiva thing",
		"activateThingParameters": "Parameters to activate thing",
		"deactivateGateway": "Disattiva",
		"commands": "Comandi disponibili",
		"deactivateGatewaySuccess": "Disattivazione avvenuta con successo",
		"updateFirmwareSuccess": "Aggiornamento firmware riuscito",
		"updateFirmwareError": "Aggiornamento firmware fallito",
		"updateGatewaySuccess": "Aggiornamento riuscito",
		"deactivateGatewayRejected": "Errore disattivazione",
		"greengrassTitle": "Rilascio Greengrass",
		"greengrassResetTitle": "Resetta Greengrass",
		"otaUpdateTitle": "Aggiorna Ota",
		"rebootGatewaySuccess": "Riavvio avvenuto con successo",
		"rebootGatewayRejected": "Errore riavvio",
		"send": "Invia",
		"searchThingsPlaceholder": "Cerca per ID, SERIAL, ALIAS",
		"snapKeyRequiredMessage": "Devi inserire una snap key",
		"installFlagsRequiredMessage": "Devi inserire gli install flags",
		"serialRequiredMessage": "Devi inserire il serial number",
		"devTypeRequiredMessage": "Devi inserire il tipo",
		"makerRequiredMessage": "Devi inserire il produttore",
		"sites": "Siti",
		"softwareCatalogue": "Catalogo software",
		"firmwareUpdate": "Aggiorna Firmware",
		"searchingFilters": "Filtri di Ricerca",
		"startDate": "Data Inizio Deploy",
		"startDateRange": "Intervallo data inizio distribuzione",
		"endDate": "Data Fine Deploy",
		"endDateRange": "Intervallo data fine distribuzione",
		"from": "Da",
		"to": "A",
		"operators": "Operatori",
		"packagesDetail": "Dettaglio Pacchetti",
		"gatewayId": "ID Gateway",
		"gatewayThings": "Thing del Gateway",
		"environmentPrefix": "Prefisso Ambiente",
		"deploymentId": "Id Rilascio",
		"softwareExtension": "Estensione Software",
		"key": "Percorso File",
		"period": "Durata",
		"gatewayType": "Tipo Di Gateway",
		"gatewayTypeShort": "Tipo GW",
		"thingTypeShort": "Tipo Thing",
		"tooltipEnvPref": "Prefisso Ambientale",
		"tooltipProjectName": "Progetto",
		"tooltipMaker": "Produttore",
		"tooltipType": "Tipo",
		"tooltipSerialNumber": "Numero Seriale",
		"serialNumber": "Numero Seriale",
		"tooltipGtwType": "Tipo di Gateway",
		"tooltipGgInst": "Greengrass Installato",
		"tooltipThingId": "Thing ID",
		"tooltipThingAlias": "Thing Alias",
		"update": "Aggiorna",
		"deactivate": "Disattiva",
		"tooltipGeoLocalization": "Geolocalizzazione",
		"latest": "Ultima versione",
		"deploymentsHistory": "Cronologia Distribuzioni",
		"campaignManagement": "Campagne Aggiornamenti",
		"deployType": "Modalità di distribuzione",
		"status": "Stato",
		"deployDetail": "Dettaglio Distribuzione",
		"empty": "Vuoto",
		"activities": "Attività",
		"diagnostic": "Diagnostica",
		"softwareManager": "Gestione Software",
		"stopBits": "Stop Bits",
		"dataBits": "Data Bits",
		"baudRate": "Baud Rate",
		"clsid": "Clsid",
		"username": "Username",
		"password": "Password",
		"jobs": "Processi",
		"radio_type": "Tipo trasmissione",
		"ipaddress": "Indirizzo IP",
		"ipAddressNotValid": "Indirizzo IP non valido",
		"port_num": "Numero porta",
		"fillData": "Fill out data",
		"siteId": "Id sito",
		"siteName": "Nome sito",
		"removeItemTitle": "Stai eliminando l'elemento: ",
		"removeItemConfirm": "Sei sicuro?",
		"activityId": "Id attivazione",
		"chooseSite": "Seleziona un sito",
		"selectThingType": "Seleziona una tipologia",
		"portName": "Nome porta",
		"parity": "Parità",
		"domain": "Nome dominio",
		"edit": "Modifica",
		"search": "Ricerca",
		"interrogationAddress": "Indirizzo interrgoazione",
		"enablePeriodicInterrogation": "Periodo d'interrogazione",
		"modelRequiredMessage": "Modello obbligatorio",
		"radioRequiredMessage": "Tipo radio obbligatorio",
		"ipRequiredMessage": "Ip obbligatorio",
		"portRequiredMessage": "Numero porta obbligatorio",
		"portNameRequiredMessage": "Nome porta obbligatorio",
		"baudRateRequiredMessage": "Baud rate obbligatorio",
		"dataBitsRequiredMessage": "Data bits obbligatorio",
		"parityRequiredMessage": "Parità obbligatorio",
		"stopBitsRequiredMessage": "Stop bits obbligatorio",
		"clsidRequiredMessage": "Clsid obbligatorio",
		"usernameRequiredMessage": "Username obbligatorio",
		"passwordRequiredMessage": "Password obbligatoria",
		"domainRequiredMessage": "Dominio obbligatorio",
		"intAddrRequiredMessage": "Indirizzo obbligatorio",
		"latRequiredMessage": "Latitudine obbligatorio",
		"lngRequiredMessage": "Longitudine obbligatorio",
		"lat": "Latitudine",
		"lng": "Longitudine",
		"noThings": "Non ci sono things provisionate",
		"noGateways": "Non ci sono gateways",
		"noJobs": "Nessun job",
		"typeTopic": "Inserisci un topic (uno tra devices/registration, devices/monitoring, <env_prefix>/...)",
		"deviceUpdated": "Dispositivo aggiornato",
		"projectsError": "Non è stato possibile recuperare i progetti...",
		"retry": "Riprova",
		"updateThing": "Aggiorna thing",
		"successOperation": "Operazione riuscita",
		"genericError": "Errore chiamata di rete",
		"noResolved": "Non risolto",
		"noItems": "Nessun elemento",
		"noCoords": "Non georeferenziata",
		"state": "Stato",
		"statusDate": "Data Stato",
		"date": "Data",
		"creationDate": "Data creazione",
		"Details": "Dettaglio",
		"message": "Messaggio",
		"duration": "Durata",
		"commandType": "Tipo comando",
		"memory": "Memoria (usata/totale)",
		"source": "Sorgente",
		"event_type": "Tipo di Evento",
		"type": "Tipo",
		"all": "Tutti",
		"notification": "Notifiche",
		"error": "Errori",
		"timeout": "Timeout",
		"attrName": "Nome attributo",
		"attrVal": "Valore attributo",
		"operName": "Nome operazione",
		"number": "Numero",
		"mode": "Modo",
		"logStream": "Flusso Log",
		"command": "Comando",
		"device": "Dispositivo",
		"Logs": "Log",
		"Alarms": "Allarmi & Eventi",
		"Activities": "Attività",
		"Sites": "Siti",
		"Lambdas": "Lambda",
		"Gateways": "Gateways",
		"Jobs": "Jobs",
		"Job": "Dettaglio Job",
		"Gtw-detail": "Dettaglio gateway",
		"filename": "Nome file",
		"appname": "Nome app",
		"version": "Ver",
		"start": "Inizio",
		"end": "Fine",
		"save": "Salva",
		"back": "Indietro",
		"next": "Avanti",
		"showMore": "Carica altri",
		"moreInfo": "Più info",
		"IncorrectUsernameOrPassword": "Username o password errati.",
		"selectTemplate": "Selezionare Iot Gateway Template",
		"serial_number": "Numero Seriale",
		"device_type": "Tipo di Dispositivo",
		"external_id": "ID Esterno",
		"filter_tag": "Filter Tag",
		"interaction_mode": "Modalità Interazione",
		"generalInterrogationAddress": "Indirizzo di Richiesta",
		"deactivateThing": "Disattiva thing",
		"deactivateThings": "Disattiva things",
		"monitorThing": "Monitora thing",
		"thingCommands": "Comandi Thing",
		"activate": "Attiva",
		"deploymentDetail": "Dettaglio Rilascio",
		"gatewayList": "Gateways",
		"lambdasList": "Lambda",
		"alarmsList": "Allarmi",
		"jobsList": "Jobs",
		"stepFunction": "Step function",
		"amsTool": "Caricamento certificati",
		"dropzoneText1": "Trascina il file del Certificato qui",
		"dropzoneText2": "oppure sfoglia",
		"sitesList": "Siti",
		"count": "Numero Messaggi",
		"add": "Aggiungi",
		"remove": "Rimuovi",
		"reset": "Pulisci",
		"removeActivityPromptName": "Rimuovi esecuzione",
		"runActivityTitle": "Esecuzione Attività",
		"runConfirmation": "Conferma esecuzione",
		"runActivityConfirm": "Vuoi eseguire questa attività?",
		"renewCertificate": "Rinnova Certificati",
		"renew": "Rinnova",
		"renewLightGateway": "Stai per rinnovare il certificato di un light gateway, questa operazione aggiornerà i certificati di tutte le thing associate al gateway",
		"renewDirectThing": "Rinnovo del certificato per: ",
		"invalidDate": "Data Invalida",
		"connectivityHistory": "Cronologia Connessioni",
		"connection": "Connessione",
		"disconnection": "Disconnessione",
		"meanConnection": "Media Connessioni",
		"values": "Valori",
		"noAvailableData": "Nessun dato disponibile",
		"noAvailable": "Non disponibile",
		"timerange": "Selezione Temporale",
		"export": "Esporta",
		"exporting": "Esportando...",
		"showLogs": "Mostra Logs",
		"showTailLogs": "Tail Logs",
		"getHistoryLogs": "Mostra Storico Logs",
		"enableCollectLogs": "Abilita Collect Logs",
		"disableCollectLogs": "Disabilita Collect Logs",
		"successDisableCollectLogs": "Collect Logs disabilitato con successo",
		"noMoreItems": "Non ci sono più elementi da visualizzare",
		"commandInStatus": "Il comando è in stato: ",
		"monitoringSuccess": "Comando di Monitoring Inviato con Successo",
		"collectSuccess": "Comando di Collect Logs Inviato con Successo",
		"ticket": "Cartellino",
		"tickets": "Cartellini",
		"certificateRenewalSuccess": "Certificati Rinnovati con Successo",
		"detailsWindowTooltip": "Finestra di Dettaglio",
		"deviceType": "Tipo dispositivo",
		"forceDeleteTooltip": "Selezionando questa voce viene forzata la cancellazione del dispositivo dal sistema anche qualora questo non sia più connesso (se non connesso dopo 30 min)",
		"forceDeleteTooltipWithout30minWarning": "Selezionando questa voce viene forzata la cancellazione del dispositivo dal sistema anche qualora questo non sia più connesso",
		"deleteCertificateTooltip": "Selezionando questa voce il certificato utilizzato nella registrazione del device viene cancellato dal sistema e potrà quindi essere nuovamente utilizzato per una nuova completa registrazione di un device",
		"caseSensitiveField": "Campo Case Sensitive (fare riferimento alla \"DMC Guide\" per la sintassi avanzata)",
		"caseSensitiveFieldThing": "Ricerca per specifica parola chiave (case sensitive - fare riferimento alla \"DMC Guide\")",
		"directThing": {
			"deleteCertificate": "Cancella Certificato",
			"forceDelete": "Forza Eliminazione",
			"theDirectThingIs": "La Direct Thing è ",
			"editDirectThing": "Modifica",
			"communication": "Comunicazione abilitata",
			"certificateRenewalSuccess": "Certificati rinnovati con successo",
			"deactivateDirectThing": "Disattiva",
			"showMoreDirectThing": "Altre info",
			"telemetryDirectThing": "Telemetria",
			"activateDirectThing": "Attiva Direct",
			"activateDirectThingFormTitle": "Attiva Direct Thing",
			"updateDirectThingFormTitle": "Modifica Direct Thing",
			"thing_id": "ID Direct Thing",
			"updateFirmwareSuccess": "Firmware aggiornato con successo",
			"packageNotPresent": "Questi pacchetti non sono presenti nel software del catalogo, potrebbero esserci problemi durante l'installazione.",
			"packageWarning": "I pacchetti presenti nei dispositivi selezionati potrebbero non essere presenti nel software catalogue, potrebbero esserci problemi durante l'installazione.",
			"rebootDirectThingSuccess": "Direct Thing riavviata con successo",
			"maker": "Produttore",
			"radio_type": "Tipo Trasmissione",
			"serial_number": "Numero Seriale",
			"interaction_mode": "Modalità Interazione",
			"device_type": "Tipo di Dispositivo",
			"model": "Modello",
			"activateDirectThingSuccess": "Direct Thing Attivata con Successo",
			"updateDirectThingSuccess": "Direct Thing Aggiornata con Successo",
			"deactivateDirectThingSuccess": "Direct Thing Disattivata con Successo",
			"moreInfo": "Maggiori Informazioni",
			"latitude": "Latitudine",
			"longitude": "Longitudine",
			"noCustomAttributes": "Non esistono attributi custom per questo progetto",
			"functionalityDisabled": "Questa funzionalità non è abilitata per questo dispositivo"
		},
		"mqtt": {
			"connectTo": "Connetti al client",
			"disconnectTo": "Disconnetti dal client",
			"clean": "Pulisci lista messaggi",
			"connect": "Connessione alla websocket",
			"credential": "Recupero credenziali",
			"credentialRetrieved": "Credenziali ottenute",
			"noCredential": "Errore creazione MQTT client: credenziali non valide",
			"connected": "CONNESSIONE RIUSCITA",
			"noConnected:": "CONNESSIONE NON RIUSCITA",
			"listening": "Ascolto sul topic: ",
			"unsubscribe": "Annulla l'iscrizione sul topic: ",
			"disconnected": "Client disconnesso",
			"clickPlay": "Premi il tasto PLAY per connetterti",
			"timeStarted": "tempo di inizio:",
			"diagnostic": "Diagnostica/",
			"searchPlaceholder": "Trova nel payload"
		},
		"rde": {
			"removeRdePromptName": "Rimuovi Regola",
			"addRule": "Agg. Regola",
			"backToRde": "Torna a RDE",
			"ruleDetail": "Dettaglio Regola",
			"addRuleLong": "Aggiungi Regola",
			"editRule": "Modifica Regola",
			"ruleAndDispatchEngine": "Motore di Regole e Invio",
			"filter": "Filtro",
			"filterId": "ID Filtro",
			"filterType": "Tipo Di Filtro",
			"eventDetection": "Evento",
			"andConditions": "Condizioni",
			"actions": "Azioni",
			"actionsDetail": "Dettaglio Azioni",
			"ruleId": "ID Regola",
			"occurrences": "Occorrenze",
			"attributeName": "Nome Attributo",
			"value": "Valore",
			"actionType": "Tipo",
			"formatter": "Formatter",
			"region": "Regione",
			"topic": "Topic",
			"valueType": "Tipo Valore",
			"resourceName": "Nome risorsa",
			"kinesisStream": "kinesisStream",
			"method": "Metodo di richiesta",
			"authorizationType":"Tipo di Autorizzazione",
			"authorizationToken": "Token Di Autorizzazione",
			"endpoint": "Endpoint",
			"queryParams": "Parametri di Richiesta",
			"caCert": "CA Cert",
			"roleArn": "Ruolo Arn",
			"username": "Username",
			"password": "Password",
			"requestMethod": "Metodo"
		},
		"swManager": {
			"deploymentsHistory": {
				"title": "Storico Rilasci",
				"updateDeployment": {
					"title": "Aggiornamento stato di installazione",
					"action": "Aggiorna stato di installazione",
					"customStatusDesc": "Inserisci uno stato personalizzato opzionale per descrivere ulteriormente questo aggiornamento di stato",
					"customStatusPlaceholder": "Inserisci uno stato personalizzato",
					"customStatus": "Stato personalizzato",
					"installStatus": "Stato installazione",
					"success": "Stato rilascio aggiornato",
					"error": "Impossibile aggiornare lo stato del rilascio"
				}
			},
			"campaignManagement": {
				"byQueryDescription": "Una operazione massiva agisce su una lista di rilasci basati su una query. Per eseguire una operazione massiva, seleziona tutte le righe attraverso il checkbox \"seleziona tutti\" nell'intestazione della tabella"
			},
			"enableLatest": "Abilitare Latest",
			"none": "Nessuno",
			"complete_install": "installazione completata",
			"failed_install": "installazione fallita",
			"timeout_install": "timeout",
			"partial_install": "installazione parziale",
			"in_progress": "in attesa",
			"addPackage": "Agg Pacchetto",
			"addNewPackage": "Aggiungi Pacchetto",
			"gatewayTypeShort": "Tipo GW",
			"updatePackage": "Aggiorna pacchetto",
			"amsTool": "Carica certificato",
			"apiInvocation": "API Invocation",
			"appId": "App ID",
			"appName": "Nome App",
			"appVersion": "Versione",
			"appArchitecture": "Architettura",
			"appArchitectureShort": "Arch.",
			"gatewayType": "Software Gateway Type ",
			"thingType": "Software Thing Type",
			"softwareExtension": "Estensione Software",
			"softwareExtensionShort": "Est.",
			"searchSoftwareCatalogue": "Ricerca per appname esatto",
			"s3Path": "Percorso S3",
			"appVersionOperator": "Operatore",
			"gtwSoftware": "Gateway Software",
			"gtwList": "Lista Gateways:",
			"packagesToInstall": "Pacchetti Da Installare",
			"currentStack": "Stack Software",
			"firmwareUpdateParameters": "Parametri Aggiornamento Firmware",
			"options": "Opzioni",
			"installedPackages": "Pacchetti Installati",
			"rollbackPolicy": "Rollback",
			"globalRollback": "Globale",
			"individualRollback": "Individuale",
			"greenGrassDeploy": "Rilascio greengrass",
			"ggDeploySuccess": "Rilascio riuscito",
			"ggDeployRejected": "Rilascio fallito",
			"ggResetSuccess": "Greengrass resettato",
			"otaUpdateSuccess": "Ota Aggiornato",
			"otaUpdateReject": "Aggiornamento Ota fallito",
			"otaUpdateTitle": "Aggiornamento Ota",
			"description": "Descrizione",
			"deploymentStatus": "Stato Distribuzione",
			"deploymentsHistoryList": "Storico Rilasci",
			"deploymentsHistoryHint": "Selezionando/deselezionando una riga della tabella, tutte le righe con stesso ID del dispositivo verranno selezionate/&shy;deselezionate",
			"activitiesList": "Attività",
			"thingsList": "Lista Things",
			"swThingType": "Tipo Sw Thing",
			"deviceType": "Tipologia Dispositivo",
			"softwareType": "Tipo di Software",
			"deviceSoftwareType": "Tipologia SW",
			"deviceId": "ID Dispositivo",
			"softwareDetails": "Dettaglio Software",
			"detail": "Dettaglio",
			"edit": "Modifica",
			"delete": "Elimina",
			"download": "Scarica",
			"deviceTypeToSearch": "Tipo di dispositivo da ricercare",
			"gatewaysCampaign": "Campagne Gateways",
			"thingsCampaign": "Campagne Things",
			"directThingsCampaign": "Campagne Direct Things",
			"switchCampaign": "Cambia Campagna",
			"deviceTypeControl": "Il filtro sul tipo di dispositivo (gateway o Direct Thing) non viene applicato da solo, ma si combina con i filtri di ID dispostivo, tipo software e modalità di distribuzione del software.",
			"file": "Seleziona file",
			"enviroment_prefix": "Prefisso ambiente",
			"bucket": "S3 bucket",
			"downloadSoftwareCatalogue": "Scarica catalogo software",
			"downloadSoftwareCatalogueConfirm": "Stai per scaricare questo catalogo software",
			"uploadSoftwareCatalogueSuccess": "Catalogo software caricato con successo",
			"uploadSoftwareCatalogueError": "Impossibile caricare il catalogo software",
			"deleteSoftwareCatalogue": "Elimina catalogo software",
			"deleteSoftwareCatalogueConfirm": "Stai per eliminare questo catalogo software",
			"newSoftwarePackage": "Nuovo pacchetto software",
			"selectAllDeployments": "In order to enable it, uncheck select all option",
			"legacyPackagesHint": "I pacchetti legacy senza il Tipo Dispositivo non sono modificabili",
			"noPackageAvailable": "Nessun pacchetto disponibile",
			"filters": {
				"appname": "Nome",
				"architecture": "Architettura",
				"gateway_type": "Tipo gateway",
				"thing_type": "Tipo thing",
				"gatewaySoftwareType": "Tipo software gateway",
				"thingSoftwareType": "Tipo software thing",
				"software_extension": "Estensione",
				"version": "Versione",
				"description": "Descrizione",
				"environment_prefix": "Prefisso Ambiente",
				"key": "Chiave",
				"file": "Seleziona File",
				"deviceType": "Tipo Dispositivo",
				"softwareType": "Tipo Software"
			},
			"otaUpdate": {
				"name": "Nome",
				"options": "Opzioni",
				"updateTargetsArchitecture": "Architettura",
				"updateTargetsOperatingSystem": "Sistema Operativo",
				"alertFleetMessage": "Il comando potrebbe fallire se nella lista ci sono contemporaneamente gateway di tipo GENERIC e non GENERIC"
			},
			"softwareCatalogsError": "Impossibile reperire cataloghi software",
			"noSoftwareCatalogFound": "Nessun catalogo software trovato.",
			"softwareTypeShort": "Tipo SW",
			"softwareCatalogueCreateError": "Esiste già un catalogo software con gli stessi nome e versione",

			"disabledGgDeployAction": "Per abilitare, deseleziona il checkbox che seleziona tutte le righe",
			"disabledGgResetAction": "Per abilitare, deseleziona il checkbox che selezionare tutte le righe",
			"disabledOtaUpdateAction": "Per abilitare, seleziona soltanto gateway types",
			"disabledFwUpdateAction": "Per abilitare, seleziona soltanto un gateway type or un sw thing type"
		},
		"lambdas": {
			"selectLambda": "Seleziona Lambda",
			"searchLambda":  "Cerca Lambda",
			"dateRange":  "Intervallo date"
		},
		"drc": {
			"connect": "Connettiti",
			"certificate": "Certificato",
			"usernamePassword": "Username e Password",
			"tunnelAlreadyExists": "Un tunnel per il gateway selezionato è già attivo",
			"tunnelForceOpen": "Chiudi il tunnel esistente e crea un nuovo tunnel?",
			"passphraseRequired": "La passphrase è obbligatoria se è abilitata",
			"zipFilesMessageError": "Il file zip deve contenere almeno 3 file",
			"unsupportedEncryptedZip": "Gli zip criptati non sono supportati",
			"allowedFiles": "Sono consentiti 3 files: *-cert.pub, *.pub, il file privateKey non deve avere l'estensione"
		},
		"devicesComponent": {
			"connected": "connected",
			"disconnected": "disconnected"
		},
		"e2em": {
			"timeUnit": "Unità di tempo",
			"custom": "Personalizzato?",
			"customCheckNote": "Se il parametro 'Personalizzato' è abilitato, allora puoi inserire un valore intero qualsiasi come valore di input per la finestra temporale (min 60 secs)",
			"subscriptions": "Sottoscrizioni",
			"subscriptionNote": "Le regole saranno operative al più 15 minuti dopo la configurazione",
			"maxSendingTiming": "Frequenza Massima Notifica",
			"maxFrequency": "Frequenza Massima Notifica",
			"maxPeriod": "Periodo Notifica Massimo",
			"telemetryRulesCount": "N° Regole Telemetriche",
			"telemetryRules": "Regole Telemetriche",
			"businessDeviceAlarm": "Allarme Business",
			"disserviceDeviceAlarm": "Allarme Disservizio Diffuso",
			"target": "Target",
			"trendIdRules": "Regole Trend ID",
			"trendIdRule": "Regola Trend ID",
			"trendId": "Trend ID",
			"rdeRuleId": "Rde Regola ID",
			"type": "Tipo",
			"operator": "Operatore",
			"value": "Valore",
			"trendIdHighThreshold": "Soglia Max",
			"trendIdLowThreshold": "Soglia Min",
			"selectAlarmSeverity": "Selezionare il livello di severità",
			"devConfigNote1": "Se viene impostata una configurazione di soglia, verranno inoltrate anche le notifiche di connessione e/o disconnessioni dei dispositivi interessati dalla configurazione",
			"devConfigNote2": "Se il gruppo per il quale viene configurato l' allarme è di tipo PERSONALIZZATO, allora non sarà possibile settare una configurazione di allarme Telemetry/Threshold",
			"deviceConfigDetail": "Dettaglio Configurazione",
			"unsubscribe": "Disiscrivi",
			"unsubscribeL": "disiscrivi",
			"checkTelemetryAll": "Per continuare, imposta tutti i parametri della regola di telemetria",
			"checkParameters": "Per continuare, impostare almeno uno dei seguenti parametri: Soglia bassa frequenza messaggi, o Soglia alta frequenza messaggi, o una regola di telemetria",
			"defaultConfiguration": "Configurazione di Default",
			"customConfiguration": "Configurazione Personalizzata",
			"tooltipTelemetryRules": "Sono regole telemetriche impostate per una o più misure lette da un dispositivo",
			"tooltipAlarmSource": "E' il tipo di risorsa che genera gli allarmi",
			"tooltipNotificationSchedule": "E' la schedulazione delle notifiche che devono essere inviate, se settato su CONTINUOUS le notifiche verranno SEMPRE inviate",
			"notificationsSubscriptions": "Sottoscrizioni",
			"tooltipNotificationsSubscriptions": "E' il numero totale delle sottoscrizioni impostate alla notifica dell'allarme",
			"tooltipAlarmScope": "E' la specifica risorsa che genera gli allarmi",
			"tooltipGroupId": "Il 'gateway ID' per il gruppo di dispositivi connessi a questo Gateway oppure “ALL” per tutti i dispositivi nel progetto",
			"tooltipAlarmCategory": "Livello degli allarmi (DEBUG e INFO non sono considerati come veri e propri allarmi ma sono solo a scopo di sviluppo)",
			"tooltipLowerThreshold": "Numero MINIMO di messaggi attesi nella finestra temporale",
			"tooltipHigherThreshold": "Numero MASSIMO di messaggi attesi nella finestra temporale",
			"deleteSubMessage": "Vuoi cancellare la seguente sottoscrizione?",
			"deleteSubscription": "Cancellazione Sottoscrizione",
			"channelRoleArn": "Arn Ruolo Canale",
			"deleteConfigMessage": "Vuoi cancellare la seguente configurazione?",
			"defaultAlarmCategory": "Categoria Allarme Default",
			"subscribe": "Sottoscrivi",
			"subscribeConfig": "Sottoscrizione Notifica",
			"targetArn": "Arn di Destinazione",
			"roleArn": "Ruolo Arn",
			"subscribeNotification": "Sottoscrizione Notifica",
			"messageRates": "Frequenza Messaggi",
			"devConfigActions": "Azioni Configurazione Dispositivi",
			"receivers": "Destinatari",
			"e2eMonitoring": "E2E Monitoring",
			"groupId": "Id Gruppo",
			"cloudComponent": "Componente Cloud",
			"devicesGroup": "Gruppo di Dispositivi",
			"projectId": "Id Progetto",
			"alarmCategory": "Categoria Allarmi",
			"lowerThreshold": "Soglia Minima",
			"lowThld": "Soglia Minima",
			"higherThreshold": "Soglia Massima",
			"highThld": "Soglia Massima",
			"devicesConfigurations": "Configurazione Allarmi Dispositivi",
			"notificationsConfigurations": "Configurazione notifiche",
			"thresholds": "Soglie",
			"trigger": "Trigger",
			"scope": "Ambito",
			"alarmType": "Tipo di Allarme",
			"alarmTarget": "Origine Allarme",
			"alarmSource": "Origine Allarme",
			"channels": "Canali",
			"notificationId": "Id Notifica",
			"notificationFrequency": "Frequenza Notifica",
			"triggerType": "Tipo Trigger",
			"notificationsSchedule": "Schedulazione Notifiche",
			"scopeType": "Tipo Ambito",
			"scopeTarget": "Ambito di Destinazione",
			"sourceSelection": "Seleziona l'origine ",
			"sourceSelectionTitle": "Seleziona MICROSERVIZIO",
			"sourceSelectionDescription": "Gli allarmi generati dai microservizi sono già presenti nella sezione Allarmi del DMC. Qui puoi aggiungere notifiche a questi allarmi",
			"channelType": "Tipo Canale",
			"channelTarget": "Canale di Destinazione",
			"channelReceivers": "Canale di Ricezione",
			"enabled": "Abilitato",
			"active": "Attiva",
			"subscriptionArn": "Arn Sottoscrizione",
			"triggerWeekday": "Giorni",
			"time": "Ore",
			"timeUTC": "Ore (UTC)",
			"notificationWindow": "Intervallo di notifica",
			"notificationWindowDescription": "Scegliere tra CONTINUOUS, se vuoi ricevere le notifiche in qualsiasi momento, oppure SCHEDULED se vuoi riceverle soltanto durante un preciso intervallo temporale configurabile (ad esempio durante l'orario lavorativo)",
			"configure": "Configura",
			"updateConfig": "Aggiorna Configurazione",
			"updateConfigAlarm": "Aggiorna configurazione - Allarme",
			"deleteConfig": "Cancella Configurazione",
			"addConfig": "Aggiungi Configurazione",
			"addConfigTrunc": "Agg. Config.",
			"addSubscription": "Aggiungi Sottoscrizione",
			"subscriptionType": "Tipo di Sottoscrizione",
			"wizardButton": "Wizard",
			"timeWindow": "Finestra Temporale",
			"notificationConfiguration": "Configurazione notifica",
			"notificationConfigurationEdit": "Aggiorna configurazione - Notifica",
			"notificationConfigDetail": "Dettaglio Configurazione Notifica",
			"notConfigActions": "Azioni Configurazione Notifica",
			"tooltipProjectId": "Id Progetto",
			"tooltipNotificationId": "Id Notifica",
			"tooltipAlarmType": "Tipo Allarme",
			"tooltipForceAlarmCategory": "Categoria Force Alarm",
			"tooltipTrigger": "Trigger",
			"tooltipScope": "Ambito",
			"tooltipChannels": "Canali",
			"tooltipAggregatedConfig": "Configurazione Aggregata",
			"messagesNumber": "Numero messaggi",
			"disserviceShortTimeWindow": "Finestra Temporale Corta",
			"disserviceLongTimeWindow": "Finestra Temporale Lunga",
			"disserviceTimeUnit": "Unità di tempo",
			"telemetryThresholdDeviceFormTabTitle": "Telemetria/Soglie",
			"businessDeviceFormTabTitle": "Business",
			"generalDisservicesDeviceFormTabTitle": "Disservizio Diffuso",
			"infoDialog": {
				"groupIdTitle": "Target dell' Allarme",
				"groupIdDescription1": "Questo parametro rappresenta lo scopo dell'allarme",
				"groupIdDescription2": "Può essere il Gateway ID quando i targets dell' allarme sono le Things sottese a quel Gateway; Custom Group ID, quando il target dell' allarme è un gruppo di Dispositivi (Gateway e Things) definiti dall' utente e ALL, quando i targets sono tutti i dispositivi del PROGETTO",
				"businessConfigTitle": "Configurazione Allarme Business",
				"businessConfigDescription1": "Questa configurazione viene utilizzata per monitorare lo stato di disconnessione dei dispositivi associati al Target dell'allarme, all' interno di uno specifico intervallo temporale.",
				"businessConfigDescription2": "Se la soglia viene oltrepassata, all' interno della finestra temporale specificata nella configurazione, allora l' allarme scatterà.",
				"businessConfigDescription3": "Questa configurazione può essere impostata utilizzando il Wizard della tabella oppure modificando una configurazione esistente dalla colonna Azioni.",
				"disserviceConfigTitle": "Configurazione Allarme di Disservizio diffuso",
				"disserviceConfigDescription1": "Questa configurazione serve a monitorare disservizi diffusi, nello specifico è un set di finestre temporali di controllo (Finestra Temporale Corta e Finestra Temporale Lunga) sul numero di dispositivi disconnessi associati, al target dell' allarme, dall' ultimo checkpoint;",
				"disserviceConfigDescription2": "se il numero di dispositivi in allarme supera il valore settato, all' interno di una delle due Finestre Temporali, allora l' allarme scatterà",
				"disserviceConfigDescription3": "Questa configurazione può essere impostata utilizzando il Wizard della tabella oppure modificando una configurazione esistente dalla colonna Azioni",
				"lowerMessageRateConfigTitle": "Configurazione Allarme di Soglia Messaggi Minima",
				"lowerMessageRateConfigDescription1": "E' il minimo numero di messaggi attesi dai Dispositivi target dell' allarme, all' interno della finestra temporale definita, se il numero dei messaggi inviati è inferiore del valore settato nella regola, allora l' allarme scatterà.",
				"lowerMessageRateConfigDescription2": "Questa configurazione può essere impostata utilizzando il Wizard della tabella oppure modificando una configurazione esistente dalla colonna Azioni.",
				"lowerMessageRateConfigDescription3": " N.B: Non è disponibile per Target di tipo Custom Group",
				"higherMessageRateConfigTitle": "Configurazione Allarme di Soglia Messaggi Massima",
				"higherMessageRateConfigDescription1": "E' il massimo numero di messaggi attesi dai Dispositivi target dell' allarme, all' interno della finestra temporale definita, se il numero dei messaggi inviati è maggiore del valore settato nella regola, allora l' allarme scatterà.",
				"higherMessageRateConfigDescription2": "Questa configurazione può essere impostata utilizzando il Wizard della tabella oppure modificando una configurazione esistente dalla colonna Azioni.",
				"higherMessageRateConfigDescription3": "N.B: Non è disponibile per Target di tipo Custom Group",
				"telemetryRulesConfigTitle": "Configurazione Allarme di Telemetria",
				"telemetryRulesConfigDescription1": "E' un set di configurazioni definite per monitorare uno specifico Trend ID di telemetria di uno o più dispositivi appartenenti al gruppo del Target dell' allarme.",
				"telemetryRulesConfigDescription2": "Questa configurazione può essere impostata utilizzando il Wizard della tabella oppure modificando una configurazione esistente dalla colonna Azioni.",
				"telemetryRulesConfigDescription3": "N.B: Non è disponibile per Target di tipo Custom Group",
				"alarmSourceTitle": "Sorgente dell' Allarme",
				"alarmSourceDescription": "E' il tipo di sorgente che innesca l' allarme, può essere 'Devices', se la notifica è configurata per un' allarme innescato da un Dispositivo, oppure 'Cloud' se la sorgente dell' allarme è un Servizio di Piattaforma",
				"notificationScopeTargetTitle": "Target dell' Allarme Notificato",
				"notificationScopeTargetDescription": "E' l'ID del target dell' allarme per il quale è stata configurata la Notifica",
				"notificationScopeTypeTitle": "Tipo dell' Allarme Notificato",
				"notificationScopeTypeDescription": "E' il tipo dell' allarme per il quale è stata configurata la notifica, può essere 'disservice', 'business', 'project', 'group' o 'log_group'",
				"notificationScheduleTitle": "Schedulazione Notifica",
				"notificationScheduleDescription1": "E' la configurazione della schedulazione dell' invio della notifica, può essere Continua (la notifica verrà sempre inviata) oppure Schedulata (la notifica verrà inviata secondo una specifico intervallo temporale).",
				"notificationScheduleDescription2": "Può essere configurazta utilizzando il Wizard della tabella oppure cliccando sul bottone Modifica della colonna Azioni",
				"notificationSubscriptionsTitle": "Sottoscrizioni alla Notifica",
				"notificationSubscriptionsDecription1": "E' il numero di destinatari sottoscritti alla notifica.",
				"notificationSubscriptionsDecription2": "Per vedere la lista dei destinatari oppure per sottoscriversi alla notifica, cliccare sul pulsante Sottoscrivi nella colonna Azioni dellla tabella"
			},
			"formError": {
				"businessConfInvalid": "Configurazione Business invalida",
				"disserviceConfInvalid": "Configurazione Disservizi Diffusi invalida",
				"nonNullConfig": "Deve essere settata almeno una configurazione di allarme",
				"messageRatesInvalid": "Configurazione di Soglia del Rateo dei Messaggi invalida",
				"telemetryRulesInvalid": "Configurazione Regole di Telemetria invalida",
				"telemetryThldConfigInvalid": "Configurazione Telemetria/Soglie invalida",
				"invalidLongThreshold": "Settaggio Finestra Temporale Lunga invalido (min 60 secondi / max 1 settimana)",
				"invalidLongNrThreshold": "Numero di dispositivi in allarme non valido ",
				"invalidShortThreshold": "Settaggio Finestra Temporale Corta invalido (min 60 secondi / max 1 settimana)",
				"invalidShortNrThreshold": "Numero di dispositivi in allarme non valido ",
				"shortHigherLongError": "Selezione Finetre temporali non valida: la finestra Lunga deve essere più grande della finestra Corta",
				"disserviceNonEmptyFields": "Riempire tutti i campi della configurazione",
				"disserviceErrorThresholds": "Settaggio dei campi non valido",
				"businessErrorThresholds": "Selezione temporale non valida (min 60 secondi / max 24 ore)",
				"messageRatesInvalidThresholds": "Selezione delle soglie non valido, il rateo della soglia massima delle essere maggiore di quello della minima",
				"messageRatesInvalidLowThreshold": "Settaggio soglia minima invalido (min 60 secondi / max 24 ore)",
				"messageRatesInvalidHighThreshold": "Settaggio soglia massima invalido (min 60 secondi / max 24 ore)",
				"telemetryRuleInvalidThresholds": "Selezione valori di soglia non validi, la soglia Alta deve essere maggiore di quella bassa"
			},
			"wizard": {
				"devices_title": "Procedura guidata: Devices Alarm",
				"cloud_title": "Procedura guidata: Cloud Component Alarm ",
				"step_title": "Cosa vuoi monitorare?",
				"step_devicesOption": "Dispositivi (Gateway o gruppi di Things)",
				"step_cloudOption": "Componente Cloud (Microservizi della piattaforma IoT)",
				"devices_wizard": {
					"breadcrumb": "Configurazione allarmi sui dispositivi",
					"title": "Cosa vuoi fare?",
					"description": "",
					"summary": "Riepilogo",
					"newAlarm": "Configurare nuovo allarme",
					"addNotification": "Aggiungere notifica ad un allarme esistente",
					"selectAlarmType": "Quale tipo di allarme?",
					"selectNotificationType": "Per quale tipo di allarme?",
					"telemetryThresholdAlarm": "Telemetria o Soglia",
					"business": "Business",
					"disservice": "Disservizio Diffuso",
					"notificationTarget": "Target Notifica",
					"notificationAggregation": "Aggregazione Notifica",
					"notificationTargetSubDescription": "Vuoi raggruppare le notifiche in un determinato periodo di tempo? Ciò ridurrà il numero di notifiche...",
					"notificationTargetDescription": "Seleziona dalla lista una configurazione di allarme dispositivi alla quale aggiungere la notifica.",
					"notificationPeriod": "Notification period",
					"devicesAlarmType": "Tipologia allarme dispositivi",
					"alarmTarget": "Origine dell'allarme",
					"alarmsNumber": "Numero di allarmi",
					"businessAlarmTarget": "Origine dell'allarme BUSINESS",
					"businessAlarmTargetDescription": "Seleziona il TARGET dell'allarme BUSINESS: TUTTI per monitorare tutti i dispositivi appartenenti al progetto, GRUPPO per monitorare uno specifico Gruppo di dispositivi e le thing a lui connesse, oppure CUSTOM GROUP per monitorare un insieme eterogeneo di thing",
					"linkToCustomGroupView": "Per definire un nuovo CUSTOM GROUP clicca qui",
					"timeWindow": "Intervallo di tempo",
					"businessTimeWindowDescription": "Scegliere l'intervallo di tempo massimo in cui un dispositivo può rimanere disconnesso; superato questo periodo di tempo verrà generato un allarme (min 60 sec / max 24 ore)",
					"alarmSummary": "Riepilogo configurazione dell'Allarme",
					"disserviceAlarmTarget": "Origine dell'allarme DISSERVIZIO DIFFUSO",
					"disserviceAlarmTargetDescription": "Seleziona l'origine dell'allarme: ALL per scegliere tutti i dispositivi del progetto, GROUP per scegliere un Gateway e tutte le things connesse ad esso, CUSTOM GROUP per scegliere un set etereogeneo di things.",
					"alarmsNumberActivation": "Attivazione Allarme",
					"alarmsNumberActivationDescription": "Specificare il numero allarmi che si devono susseguire, in un intervallo di tempo, per far attivare l'allarme di disservizio",
					"disserviceTimeWindow": "Finestra temporale di disconnessione",
					"disserviceTimeWindowDescription": "Set the Time Window range (Min, Max)...",
					"disserviceTimeWindowMin": "Finestra Temporale Corta",
					"disserviceTimeWindowMax": "Finestra Temporale Lunga",
					"disserviceShortTimeWindow": "Finestra Temporale Corta",
					"disserviceLongTimeWindow": "Finestra Temporale Lunga",
					"disserviceTimeUnit": "Unità di tempo",
					"telemetryThresholdAlarmDesc": "Imposta questo tipo di allarme per monitorare il numero di messaggi (soglia) o un valore specifico (telemetria)",
					"addNotificationToDevicesDesc": "Aggiungi notifica ad un allarme esistente di tipo Telemetria o Soglia",
					"businessChangeDesc": "Imposta questo tipo di allarme per creare un allarme quando un dispositivo rimane disconnesso per più di un certo tempo a tua scelta",
					"disserviceChangeDesc": "Imposta questo tipo di allarme per creare un allarme quando un certo numero di dispositivi rimangono disconnessi per più di una certa finestra temporale (puoi specificare due finestre temporali)",
					"addNotificationToBusinessDesc": "Aggiungi notifica ad un allarme esistente di tipo Business",
					"addNotificationToDisserviceDesc": "Aggiungi notifica ad un allarme esistente di tipo Disservizio Diffuso",
					"lowMessageRate": "Minima frequenza messaggi",
					"highMessageRate": "Massima frequenza messaggi"
				},
				"cloud_wizard": {}
			},
			"wizardAddNotificationTitle": "Vuoi aggiungere una Notifica all'allarme configurato?",
			"wizardBusinessAlarmNotification": "Aggiungi una NOTIFICA ad un allarme BUSINESS esistente",
			"wizardDisserviceAlarmNotification": "Aggiungi una NOTIFICA ad un allarme DISSERVIZIO DIFFUSO esistente",
			"wizardSelectdeviceAlarmTitle": "Seleziona alarme da configurare",
			"wizardAlarmScope": "Origine dell'allarme",
			"wizardAlarmScopeDescription": "Quale Dispositivo vuoi monitorare? TUTTI per monitorare tutti i dispositivi appartenenti al progetto, oppure GRUPPO per monitorare uno specifico Gruppo di dispositivi e le thing a lui connesse",
			"aggregatedConfiguration": "Configurazione Aggreggata",
			"aggregatedTimeInterval": "Intervallo di Aggregazione",
			"timeInterval": "Intervallo di Tempo (sec)",
			"minSec": "min 60sec",
			"wizardNotificationSummaryTitle": "Riepilogo configurazione della Notifica",
			"wizardLowThresholdDescription": "vuoi monitare se i dispositivi inviano ALMENO un certo numero di messaggi in un intervallo di tempo? Puoi settare una soglia, oppure saltare questo passaggio",
			"wizardLowThresholdNote": "Fintanto che il dispositivo non comunica almeno una volta, dopo la creazione di questa configurazione di allarme, l 'allarme non verrà generato (Cold Start Effect)",
			"wizardHighThresholdDescription": "Vuoi monitare se i dispositivi inviano AL MASSIMO un certo numero di messaggi in un intervallo di tempo? Puoi settare una soglia, oppure saltare questo passaggio",
			"atLeast": "Minimo",
			"atMost": "Massimo",
			"messagesIn": "messaggi in",
			"addNotificationDescription": "Se non configuri la notifica, l’allarme apparirà comunque nella sezione «Allarmi» della DMC. Inoltre potrai aggiungere la notifica anche in un secondo momento.",
			"notificationAggregationTitle": "Aggregazione delle notifiche",
			"subscriptionDescription": "Seleziona il canale sul quale desideri ricevere le notifiche per gli allarmi",
			"subscriptionTitle": "CANALI per sottoscrizione",
			"telemetryDescription": "Vuoi monitorare gli specifici valori (trendId) assegnati dai device?",
			"wizardCompleted": "Wizard Completato",
			"warningSelectionMatch": "Hai scelto una configurazione già esistente. Se prosegui, modificherai la configurazione esistente",
			"addThresholdBtn": "AGGIUNGI SOGLIA",
			"createNotificationTip": "Vuoi essere notificato quando viene generata la notifica?",
			"deviceAlarmConfigurationTitle": "Configurazione Allarme Dispositivi:",
			"timeIntervalLabel": "Intervallo Temporale:",
			"notificationWindowLabel": "FINESTRA di Notifica:",
			"warningParameterDisabled": "Parametro disabilitato perché hai già impostato l'aggregazione delle notifiche",
			"timingConfigurationLabel": "Configurazione temporale",
			"groupNotificationNote": "Vuoi raggruppare le notifiche in un determinato periodo di tempo? Questo ridurrà il numero di notifiche prodotte dallo stesso tipo di allarme all'interno della finestra temporale selezionata",
			"notificationTimeWindowTitle": "Intervallo di tempo",
			"aggregateNotificationQuestion": "Vuoi aggregare le notifiche per l' allarme selezionato? In tal caso verranno raggruppati tutti gli allarmi generati in quell'intervallo di tempo (min 60 sec)",
			"business": "Business",
			"disservice": "Disservizio Diffuso",
			"disconnectionWindowThreshold": "Finestra Temporale di Disconnessione",
			"disconnectionWindowThresholds": "Finestre Temporali di Disconnessione",
			"deviceNrThreshold": "Soglia Dispositivi In Allarme",
			"deviceInAlarmNr": "Dispositivi in Allarme"
		},
		"landingPage": {
			"onlineCard": "Online",
			"exportDataBtnLabel": "Esporta Dati",
			"devicesCountHeaderLabel": "Dispositivi Totali",
			"gatewaysHeaderLabel": "Gateways",
			"thingsHeaderLabel": "Things",
			"directThingsHeaderLabel": "Direct Things",
			"alarmTimeseriesHeaderLabel": "Allarmi",
			"activationTimeseriesHeaderLabel": "Dispositivi e Attivazioni",
			"map": "Nazione",
			"devicesMap": "Apri Mappa Dispositivi",
			"total": "Totali",
			"online": "Online",
			"offline": "Offline",
			"timeFilterMonths3": "3 Mesi",
			"timeFilterMonths6": "6 Mesi",
			"timeFilterMonths12": "1 Anno",
			"chart_alarmsLabel": "Allarmi",
			"chart_alarmsDevicesLabel": "Allarmi/Dispositivi",
			"chart_devicesLabel": "Dispositivi",
			"chart_activationsLabel": "Attivazioni",
			"chart_month": {
				"january": "Gennaio",
				"february": "Febbraio",
				"march": "Marzo",
				"april": "Aprile",
				"may": "Maggio",
				"june": "Giugno",
				"july": "Luglio",
				"august": "Agosto",
				"september": "Settembre",
				"october": "Ottobre",
				"november": "Novembre",
				"december": "Dicembre"
			}
		},
		"cloudwatchLogs": {
			"logStream": "Flussi Di Log",
			"lastEventTimestamp": "Ora Ultimo Evento",
			"timeStamp": "Timestamp",
			"Date": "Data",
			"message": "Messaggio",
			"logSeverity": "Severità Log",
			"logCategory": "Categoria Log",
			"period": "Periodo",
			"periodHint": "Il periodo deve essere un valore intero compreso nell'intervallo [30, 86400] (secondi). Se non fornito,  il valore di default sarà 60 secondi",
			"periodMinError": "Il periodo deve essere maggiore di 30",
			"periodMaxError": "Il periodo deve essere minore 86400",
			"timeout": "Timeout",
			"timeoutHint": "Il timeout deve essere un valore intero compreso nell'intervallo [300, 172800] (secondi). Se non fornito,  il valore di default sarà illimitato",
			"timeoutMinError": "Il timeout deve essere maggiore di 300",
			"timeoutMaxError": "Il timeout deve essere minore di 172800",
			"calendarHint": "Seleziona un intervallo temporale",
			"collectLogsAlreadyEnabled": "Il comando Collect Logs è già abilitato. Cliccando il bottone Send, il comando verrà disabilitato.",
			"collectLogsExpire": "Il comando Collect Logs scadrà il: ",
			"noDataForFilter": "Non sono presenti logs per la combinazione (filtro, data) selezionati",
			"noDataInCloudwatch": "Non sono presenti logs all'interno di Cloudwatch per questo device",
			"previous": "Precedente",
			"next": "Successivo",
			"filterPattern": "Pattern da cercare",
			"timeRange": "Periodo",
			"downloadLogsConfirm":"Numero di logs da esportare: {{totalLogs}}; Procedere con l'esportazione ?",
			"logsHeaderTime":"Timestamp",
			"logsHeaderMessage":"Messaggio",
			"timerMessage": "Nessun log più recente disponibile, riprova tra ",
			"seconds": "secondi",
			"loadingMore": "Caricamento nuovi log"
		},
		"profiling": {
			"title": "Profilo Utente",
			"availableFeaturesLabel": "Funzionalità disponibili",
			"groupDescription": {
				"LandingPageGroup": "Consente l'accesso alla Landing Page della DMC e ai dati di sintesi relativi al progetto.",
				"LandingPageExportGroup": "Consente l'export in formato xlsx dei dati di sintesi riportati nella Landing Page.",
				"DevicesGroup": "Consente l'accesso alla lista di tutti i dispositivi (GW e Things) registrati per il progetto.",
				"DevicesDeviceSelectionGroup": "Consente di accedere alle informazioni di dettaglio dei dispositivi per la loro gestione.",
				"DiagnosticGroup": "Abilita agli strumenti di diagnostica messi a disposizione per l'analisi di eventuali problemi in fase di deploy del progetto.",
				"OperationsGroup": "Abilita agli strumenti messi a disposizione per le normali attività di operation sulla soluzione.",
				"TroubleshootingFixGroup": "Abilita agli strumenti di diagnostica messi a disposizione per l'analisi e la risoluzione di eventuali anomalie rilevate.",
				"SoftwareCatalogGroup": "Abilita al catalogo dei pacchetti software, che è possibile andare poi ad installare sui vari dispositivi gestiti. Mediante l'accesso al catalogo è quindi possibile andare a caricare e rimuovere i pacchetti software.",
				"CMGroup": "Abilita all'accesso in visualizzazione delle campagne di installazione dei pacchetti software, sui dispositivi registrati per il progetto.",
				"CMCampaignManagementGroup": "Consente di andare a configurare ed lanciare le campagne di installazione dei pacchetti software, sui dispositivi registrati per il progetto.",
				"IoTConfigurationsGroup": "Abilita agli strumenti di configurazione, messi a disposizione per la piattaforma IoT, che consentono di impostare specifiche funzionalità.",
				"CustomLinkGroup": "Abilita l'accesso diretto ad eventuali pagine custom sviluppate a supporto specifico del progetto.",
				"ProfilingGroup": "Nessuna informazione disponibile.",
				"Segregation":"Segregation",
				"UamGroup": "Consente di accedere alle metriche di utilizzo delle varie componenti che vanno a costituire la soluzione.",
				"TicketsManagementGroup": "Abilita la visualizzazione di tutti i ticket aperti per il progetto selezionato"
			},
			"legendLabels": {
				"enabled": "Abilitato",
				"disabled": "Disabilitato",
				"noCompAC": "Accesso Completo"
			}
		},
		"stepFunctions": {
			"deleteActionDisabledTooltip": "Questa Azione è abilitata solo per Step Function in stato IN_CORSO, se l'UTENTE ha i corretti permessi per la gestione delle Step Functions oppure se il progetto selezionato supporta questa funzionalità",
			"deleteJobTitle": "Cancellazione Processo Step Function",
			"deleteJobMessage": "Vuoi cancellare il processo di questa Step Function?",
			"deleteSuccess": "Step function eliminata con successo",
			"deleteError": "Impossibile eliminare step function"
		},
		"chartFilter": {
			"placeholder": "Nessun valore selezionato"
		},
		"uam": {
			"placeholder": "Nessun servizio selezionato",
			"usageTimeseriesHeaderLabel": "Uam",
			"noServicesAvailable": "Nessun servizio disponibile"
		},
		"incidents": {
			"targetName": "Target",
			"openTicketSuccess": "Cartellino Aperto corretto con il numero: ",
			"openIncidents": "Apertura Cartellino",
			"ticketsManagement": "Gestione Ticket",
			"ticketDetail": "Dettaglio gestione Ticket",
			"backTicketDetail": "Torna a Gestione Ticket",
			"number": "Numero Cartellino",
			"tsCreated": "Data di Creazione",
			"userId": "ID Utente",
			"id": "ID",
			"location": "Luogo",
			"priority": "Priorità",
			"state": "Stato",
			"opened": "Aperto",
			"targetId": "ID Obiettivo",
			"openTicket": "Nuovo",
			"caller": "Chiamante",
			"category": "Categoria",
			"subcategory": "Sottocategoria",
			"issue": "Problema",
			"urgency": "Urgenza",
			"service": "Servizio",
			"affectedCi": "Ci Coinvolto",
			"country": "Nazione",
			"assignedTo": "Assegnato a",
			"company": "Azienda",
			"assignmentGroup": "Gruppo di assegnazione",
			"environment": "Ambiente",
			"impactedUsers": "Utenti impattati",
			"degradationType": "Tipo Degradazione",
			"impact": "Impatto",
			"shortDescription": "Descrizione breve",
			"description": "Descrizione"
		},
		"amsTools": {
			"infoPanelLabel": "Informazioni",
			"certificatePanelLabel": "Certificato",
			"environment": "Ambiente",
			"stage": "Stage",
			"apm": "APM",
			"bucketS3": "Bucket S3",
			"fileSelected": "File selzionato",
			"pathS3": "Path: ",
			"wrongFileMessage": "I certificati possono essere caricati solo in un archivio .tar.gz",
			"upload": "CARICA",
			"fileUploading": "Caricamento file in corso...",
			"uploadSuccessMessage": "File uploaded successfully",
			"uploadErrorMessage": "Oops, something went wrong. Please try again."
		},
		"customGroup": {
			"removeCustomGroupPromptName": "Rimuovi Gruppo personalizzato",
			"nameTooLong": "Il nome scelto supera i 64 caratteri",
			"addCustomGroup": "Nuovo Gruppo",
			"onlyGateway": "Solo gateway",
			"allThings": "Tutte le things",
			"invalidGatewayName": "Nome Gateway non valido",
			"invalidThingName": "Nome Thing non valido",
			"invalidDirectThingName": "Nome Direct Thing non valido",
			"groupModifySuccess": "Gruppo modificato correttamente",
			"newGroupSuccess": "Nuovo Gruppo creato correttamente",
			"customGroup": "Gruppo Personalizzato",
			"modifyCustomGroup": "Modifica gruppo personalizzato",
			"newCustomGroup": "Nuovo gruppo personalizzato",
			"likeSearch": "Ricerca generica",
			"punctualSearch": "Ricerca puntuale",
			"searchThing": "Cerca tra le things selezionate",
			"selectedThings": "Dispositivi selezionati",
			"copyGroupWarning": "Sei in modalità duplica; in questo modo puoi creare un nuovo gruppo con un nome differente e gli stessi dispositivi.",
			"gatewayAlreadyPresent": "Getaway già presente",
			"thingAlreadyPresent": "Device già presente",
			"invalidNameCharacter": "I caratteri accentati o speciali (es. @, #, $, %, &, *) non sono validi",
			"groupsListError":"Impossibile scaricare tutti i gruppi personalizzati, riprovare",
			"segregationCreateError":"L'utente non è autorizzato a eseguire questa operazione perchè questa funzione non è disponibile per dispositivi appartenenti a Nazioni differenti.",
			"deleteSuccess": "Gruppo personalizzato rimosso con successo",
			"deleteError": "Impossibile rimuovere il gruppo personalizzato"
		},
		"certificateExpDate":"Data scadenza Certificato ",
		"certificateAuthority":"Cert. Authority",
		"segregation": {
			"title": "Segregazione",
			"clusters": "Cluster",
			"cluster": "Cluster",
			"device": "Dispositivo",
			"devices": "Dispositivi",
			"countries": "Nazioni",
			"searchbar":"Cerca tramite ID, numero seriale",
			"warning":"Attenzione",
			"deleteMessage":"Procedere alla cancellazione del Cluster <strong>{{cluster}}</strong> ?",
			"multiSelectExplain":"Per eseguire un azione su più dispositivi, selezionare dispositivi con gli stessi paesi",
			"newCluster":"Nuovo Cluster",
			"create":"Crea",
			"selectedDevices":"Dispositivi Selezionati",
			"name":"Nome",
			"serialNumber":"Numero Seriale",
			"noCountry":"Non esistono country assegnati a questo cluster",
			"searchCluster":"Cerca per Cluster, Nazione",
			"typeToSearch":"Digita per cercare",
			"typeToSearchDots":"Digita per cercare...",
			"message":{
				"performAction":"Per eseguire un'azione su più Dispositivi, selezionare Dispositivi con la stessa Nazione.",
				"limitations":"Per ogni richiesta di associazione Dispositivi ad una Nazione, ci sono alcune limitazioni:",
				"gatewaysNumber":"50 Gateways;",
				"devicesNumber":"400 Things o Direct Thing."
			},
			"response":{
				"createdCluster":"Cluster creato con successo",
				"createdClusterError":"Errore durante la creazione del cluster",
				"existingClusterError":"Il cluster {{cluster}} è già esistente",
				"editCluster":"Cluster modificato con successo",
				"editClusterError":"Errorre durante la modifica del cluster",
				"deleteCluster":"Cluster cancellato con successo",
				"deleteClusterError":"Errore durante la cancellazione del cluster",
				"editDevice":"Device modificato con successo",
				"editDeviceError":"Errore durante la modifica del dispositivo"
			}
		},
		"fileTransfers": {
			"uploadFile": "Carica File",
			"downloadFile": "Scarica File",
			"uploadFileToDevice": "Carica file sul device",
			"downloadFileFromS3": "Scarica file dalla repository",
			"downloadFileFromDevice": "Scarica file dal device",
			"filename": "Nome del file",
			"localFilePath": "Path locale del dispositivo da salvare",
			"deviceLocalFilePathForTransferToS3": "Path locale del dispositivo",
			"uploadInProgress": "Caricamento in corso",
			"transferingFileToDevice": "Trasferimento file su dispositivo",
			"downloadFromDeviceInProgress": "Download dal device in corso",
			"uploadToS3InProgress": "Caricamento su repository in corso",
			"downloadInProgress": "Download in corso",
			"downloadError": "Impossibile scaricare il file",
			"uploadGenericError": "Impossibile caricare il file",
			"fileTransferComplete": "Trasferimento file completato",
			"noFiles": "Al momento non ci sono file da scaricare",
			"downloadInfo": "L'operazione di trasferimento file potrebbe richiedere alcuni minuti, anche per file di piccole dimensioni.",
			"onDownloadCompleted": "Ad operazione conclusa, verrà visualizzato un messaggio a display con l'esito del trasferimento file.",
			"uploadError": "La cartella di upload del file sul dispositivo non esiste oppure non ci sono i permessi di scrittura.",
			"genericError":"Si è verificato un errore durante il trasferimento del file.",
			"maxContentSize":"La dimensione del file eccede la massima consentita.",
			"fileNotExist":"Il file selezionato non esiste.",
			"inputPlaceholder":"es. /localfolder/filename",
			"inputPlaceholderUpload":"es. /localfolder",
			"bottomSheetDontCloseMessage":"Non chiudere per verificare l'esito dell'operazione."
		}
	},
	"deviceList": {
		"devicesExporting": "Esporta Dispositivi",
		"devicesExportTotalItems": "Numero di dispositivi da esportare",
		"devicesExportConfirm": "questa operazione potrebbe richiedere molto tempo, vuoi procedere all'esportazione?"
	},
	"postman": {
		"title": "API Invocation",
		"backInvocation": "Torna a Invocation",
		"baseUrl": "Base",
		"baseRequired": "Base è un campo richiesto",
		"urlRequired": "URL è un campo richiesto",
		"method": "Metodo",
		"methodRequired": "Metodo è un campo richiesto",
		"formNotValid": "La form non è valida",
		"invoke": "Invoca",
		"apiResults": "Risultato di",
		"close": "Chiudi",
		"corsErrorMsg": "La tua azione non ha restituito risultati. Potrebbe esserci stato un problema di CORS",
		"urlNotFound": "o la url che hai inserito non è stata trovata",
		"noVerticalApi": "Non hai le autorizzazioni per effettuare questa azione"
	},
	"This command is used to set the internal clock of devices": "Questo comando è usato per settare l'orario interno dei dispositivi",
	"Set or change device s time": "Imposta l'orario del dispositivo",
	"Synchronize": "Sincronizza",
	"Timezone": "Fuso orario",
	"Meters to update": "Misuratori da aggiornare",
	"Preview": "Anteprima",
	"Send": "Invio",
	"Time": "Orario",
	"Synchronize Clock": "Sincronizza orologio",
	"This command is used to set checking clock synchronization": " Questo comando è usato per settare il controllo della sincronizzazione dell'orologio",
	"Enable or disable synchronization": "Abilita o disabilita la sincronizzazione",
	"Session id": "Id sessione",
	"Date sending command": "Data invio comando",
	"Pending": "In attesa",
	"PC Clock": "Orologio PC",
	"Selected": "Selezionati",
	"Expiration Timestamp": "Expiration Timestamp",
	"Auto Update": "Auto Aggiornamento",
	"Command failed": "Impossibile impostare l'orario",
	"Command succeeded": "Aggiornamento eseguito",
	"Waiting for progress": "Invio comando in esecuzione",
	"Data invio comando": "Data invio comando",
	"State": "Stato",
	"Potenza attiva (senza telecontrollo)": "Potenza attiva (senza telecontrollo)",
	"Update": "Aggiornamento",
	"Auto Update Clock": "Auto Aggiornamento Orario",
	"Update Firmware": "Aggiorna Firmware",
	"Update device s firmware": "Aggiorna il firmware del misuratore",
	"Firmware Update": "Aggiornamento Firmware",
	"Commands List": "Lista Comandi",
	"View Charts": "Visualizza Grafici",
	"Job Id": "Job Id",
	"Date Creation": "Data Creazione",
	"Status": "Stato",
	"Last Update": "Ultimo Aggiornamento",
	"Last Modified": "Ultima Modifica",
	"Search job": "Cerca Job",
	"Succeeded": "Completato",
	"SharePoint unavailable": "SharePoint non disponibile",
	"Failed": "Fallito",
	"Waiting": "In attesa",
	"PleaseWait": "Attendere prego",
	"Timeout expired": "Tempo scaduto",
	"Job could not be sent": "Job non inviato",
	"Change Language": "Lingua",
	"Select Project": "Seleziona Progetto",
	"AlarmNotifications": "Notifiche",
	"NoNotification": "Non ci sono notifiche",
	"Yes": "Si",
	"No": "No",
	"detailsWindow": {
		"detailsWindowTitle": "Dettaglio",
		"environment_prefix": "Prefisso Ambiente",
		"device_id": "Device ID",
		"alarms": "Allarmi",
		"searchable_thing_type": "Tipo di Thing ricercabile",
		"maker": "Maker",
		"timestamp_activated": "Data di Attivazione",
		"device_type": "Tipo di Dispositivo",
		"serial_number": "Numero Seriale",
		"monitoring": "Monitoraggio",
		"device_state": "Stato del dispositivo",
		"greengrass_group": "Gruppo Greengrass",
		"thing_id": "Thing ID",
		"collectlogs": "Colleziona Logs",
		"thing_type": "Tipo Thing",
		"geolocalization": "Geo-Coordinate (lon, lat)",
		"lat": "Latitudine",
		"lon ": "Longitudine",
		"things_in_error": "Things in errore",
		"gateway_type": "Tipo di Gateway",
		"sites": "Sito",
		"sw_eiidg-agent": "Eiidgn Agent",
		"sw_APP1": "Eiidg App1",
		"sw_eiidg-bpl-service": "Eiidg bpl Service",
		"sw_eiidg-core": "Eiidg Core",
		"sw_eiidg-dd-dlms": "Eiidg dd dlms",
		"sw_eiidg-dd-iec104": "Eiidg dd iec104",
		"sw_eiidg-dd-modbus": "Eiidg dd Modbus",
		"sw_eiidg-dd-mqtt": "Eiidg dd Mqtt",
		"sw_eiidg-iam-service": "Eiidg iam Service",
		"sw_eiidg-localproxy": "Eiidg localproxy",
		"sw_eiidg-thing-mapper": "Eiidg thing-mapper",
		"sw_gg_core": "GG Core",
		"sw_is_gg_installed": "GG installazione"
	},
	"other": {
		"since": "da",
		"showDetailsTooltip": "Mostra dettagli",
		"showTicketManagement": "Mostra ticket",
		"details": "Dettagli",
		"loadMore": "Mostra Altro",
		"formIsNotValid": "Form is not valid",
		"noResults": "Nessun risultato",
		"formExtensionNotValid": "L'estensione del software non combacia con l'estensione del file",
		"exampleAbbreviation": "Es",
		"alignSoftware": "Allinea software",
		"required": "Obbligatorio",
		"optional": "Opzionale"
	},
	"components": {
		"table": {
			"actions": "Azioni",
			"enterPage": "Inserire una pagina da 1 a {{pages}}",
			"of": "di",
			"pageCounters": "Pagina {{page}} di {{pages}}",
			"pageNumber": "Pagina {{page}}",
			"noPages": "Nessuna pagina",
			"pageValidation": "Inserire una pagina tra 1 e {{pages}}",
			"rowsPerPage": "Righe per pagina",
			"manageColumns": "Seleziona colonne",
			"selectPage": "Seleziona una pagina",
			"selectRow": "Seleziona riga",
			"resetColumnsSize": "Reimposta larghezza colonne",
			"noRows":"Nessun risultato"
		},
		"datetime-range-picker": {
			"from": "Dal",
			"to": "Al",
			"hours": "Ore",
			"minutes": "Minuti",
			"today": "Oggi",
			"now": "Ora",
			"select": "Seleziona date",
			"invalidRange": "Intervallo non valido"
		},
		"date-range-picker": {
			"select": "Seleziona date"
		},
		"select": {
			"defaultLabel": "Seleziona opzione...",
			"noOptions": "Nessuna opzione"
		},
		"multiSelect": {
			"defaultLabel": "Seleziona opzioni...",
			"noOptions": "Nessuna opzione"
		},
		"cloudwatch": {
			"hideMetadata": "Nascondi metadati",
			"groupByTimestamp": "Raggruppa per timestamp"
		}
	},
	"fields": {
		"timestamp": "Data",
		"type": "Tipo",
		"project": "Progetto",
		"source": "Origine",
		"message": "Messaggio",
		"status": "Stato"
	},
	"filters": {
		"certificateExpiration": "Scad. certificato",
		"command": "Comando",
		"commonName": "Nome",
		"dateRange": "Intervallo di Tempo",
		"deviceState": "Stato",
		"deviceType": "Tipo dispositivo",
		"id": "ID",
		"maker": "Produttore",
		"message": "Messaggio",
		"country":"Nazione",
		"model": "Modello",
		"region": "Regione",
		"status": "Stato",
		"timestamp_created": "Data di creazione",
		"type": "Tipo"
	},
	"menu": {
		"alarms": "Allarmi",
		"logs": "Log"
	},
	"pages": {
		"logs": {
			"search": "Cerca per origine",
			"detailsTitle": "Dettagli del log"
		},
		"alarms": {
			"detailsTitle": "Dettagli dell'allarme"
		},
		"deploymentsHistory": {
			"releaseControls": {
				"title": "Rilascio Software",
				"subtitle": "Che cosa vuoi fare?",
				"greengrassDeploy": "Rilascio Greengrass",
				"greengrassReset": "Resetta Greengrass",
				"otaUpdate": "OTA Update",
				"firmwareUpdate": "Aggiorna Firmware"
			},
			"details": {
				"environment_prefix": "Prefisso Ambiente"
			}
		}
	},
	"datetime": {
		"weekday": {
			"monday": "Lunedì",
			"tuesday": "Martedì",
			"wednesday": "Mercoledì",
			"thursday": "Giovedì",
			"friday": "Venerdì",
			"saturday": "Sabato",
			"sunday": "Domenica"
		},
		"month": {
			"january": "Gennaio",
			"february": "Febbraio",
			"march": "Marzo",
			"april": "Aprile",
			"may": "Maggio",
			"june": "Giugno",
			"july": "Luglio",
			"august": "Agosto",
			"september": "Settembre",
			"october": "Ottobre",
			"november": "Novembre",
			"december": "Dicembre"
		}
	},
	"toaster": {
		"failedConfiguration":"Configurazione Fallita: L'utente non è autorizzato a eseguire questa operazione",
		"configureFail": "Configurazione Fallita",
		"businessSuccess": "Configurazione dell'allarme aziendale aggiunta con successo",
		"disserviceSuccess": "Configurazione allarme disservizio aggiunta con successo",
		"subscribedSuccessfully": "Sottoscrizione avvenuta con successo",
		"configurationUpdatedSuccess": "Configurazione aggiornata con successo",
		"configurationUpdatedError": "Impossibile aggiornare la configurazione",
		"configurationDeletedError": "Impossibile eliminare la configurazione",
		"configurationDeletedSuccess": "Configurazione eliminata con successo",
		"subscribedToConfigSuccess": "Sottoscrizione effettuata con successo",
		"subscribedToConfigError": "Errore di sottoscrizione",
		"subscriptionDeletedSuccess": "Sottoscrizione eliminata con successo",
		"subscriptionDeletedError": "Impossibile eliminare la sottoscrizione",
		"configurationCreatedSuccess": "Configurazione creata con successo",
		"configurationCreatedError": "Impossibile create la configurazione"
	},
	"softwareCatalogue": {
		"deleteSuccess": "Catalogo Software eliminato con successo",
		"deleteError": "Impossibile eliminare catalogo software"
	},
	"validators":{
		"alphaDash":"Deve contenere solo lettere, numeri e trattini (- e _)"
	},
	"validation": {
		"required": "Campo obbligatorio",
		"maxlength": "La massima lunghezza ammessa è {{length}}",
		"asciiCharactersOnly": "Inserisci solo caratteri ASCII",
		"basicCharsOnly": "Puoi inserire solo lettere, numeri, _ e -",
		"extendedCharsOnly": "Puoi inserire solo lettere, numeri, virgole, ., _, -, @, /, : e #",
		"forcedFilename": "Il nome del file deve essere \"%FILENAME%\""
	},
	"things": {
		"alignSoftware": "Allinea Software",
		"alignSoftwareDescription": "Stai per inviare un comando di allineamento software verso il gateway",
		"alignSoftwareError": "Impossibile inviare il comando di allineamento software al gateway",
		"alignSoftwareSuccess": "Comando di allineamento software inviato al gateway con successo",
		"selectionLimitError": "Hai selezionato più di {{limit}} things, non puoi eseguire l'azione",
		"firmwareUpdateSuccess": "Comando di aggiornamento firmware inviato al gateway",
		"firmwareUpdateError": "Impossibile inviare il comando di aggiornamento firmware al gateway",
		"missingInSwCatalogueError": "Il pacchetto %name versione %version non esiste nel catalogo software. Vuoi continuare?",
		"softwareThingType": "Tipo Software Thing",
		"activateThingError": "Impossibile inviare il comando di attivazione thing",
		"activateThingSwCatalogueError": "Il software indicato non esiste o non è valido per la thing",
		"updateThingSuccess": "Thing aggiornata con successo",
		"updateThingError": "Impossibile aggiornare la thing"
	},
	"reindex":{
		"errorMessage":"Reindicizzazione in corso: per favore riprova più tardi"
	}
}
